__init__.py
result.py
tonkinese_grid.py
tonkinese_grid-2024.0.0a7.dist-info/LICENSE
tonkinese_grid-2024.0.0a7.dist-info/METADATA
tonkinese_grid-2024.0.0a7.dist-info/WHEEL
tonkinese_grid-2024.0.0a7.dist-info/top_level.txt
tonkinese_grid-2024.0.0a7.dist-info/RECORD
