Metadata-Version: 2.1
Name: tonkinese-grid
Version: 2024.0.0a7
Summary: A python library to read and write a subset of TextGrid file format
Author: RibosomeK
License: Copyright (c) <2024> <RibosomeK>
Keywords: TextGrid
Requires-Python: >=3.8
License-File: LICENSE
